credence/__init__.py
credence/github_fetcher.py
credence-0.2.0.dist-info/licenses/LICENSE
credence-0.2.0.dist-info/METADATA
credence-0.2.0.dist-info/WHEEL
credence-0.2.0.dist-info/top_level.txt
credence-0.2.0.dist-info/RECORD
