Metadata-Version: 2.4
Name: credence
Version: 0.2.0
Summary: A simple package to fetch files by number from a GitHub repository
Home-page: https://github.com/Tanmay-24/CL3
Author: Tanmay
Author-email: Tanmay <tanmay@example.com>
License: MIT
Project-URL: Homepage, https://github.com/Tanmay-24/CL3
Project-URL: Repository, https://github.com/Tanmay-24/CL3
Keywords: code,fetcher,github
Classifier: Development Status :: 3 - Alpha
Classifier: Intended Audience :: Developers
Classifier: Programming Language :: Python :: 3
Classifier: License :: OSI Approved :: MIT License
Requires-Python: >=3.6
License-File: LICENSE
Requires-Dist: requests>=2.28.0
Dynamic: author
Dynamic: home-page
Dynamic: license-file
